sayHelloPackage/__init__.py
sayHelloPackage/say.py
sayHelloPackage-0.1.0.dist-info/LICENSE
sayHelloPackage-0.1.0.dist-info/METADATA
sayHelloPackage-0.1.0.dist-info/WHEEL
sayHelloPackage-0.1.0.dist-info/top_level.txt
sayHelloPackage-0.1.0.dist-info/RECORD
