Metadata-Version: 2.1
Name: sayHelloPackage
Version: 0.1.0
Summary: just an example package
Home-page: https://github.com/lalala/example-package-repo
Author: Veronika Anikina
Author-email: lalala@gmail.com
License: UNKNOWN
Platform: UNKNOWN
Requires-Dist: numpy (<=1.17.2)
Requires-Dist: pandas (==1.3.4)
